server.py
mseep_lodestar_mcp-0.1.4.dist-info/METADATA
mseep_lodestar_mcp-0.1.4.dist-info/WHEEL
mseep_lodestar_mcp-0.1.4.dist-info/entry_points.txt
mseep_lodestar_mcp-0.1.4.dist-info/top_level.txt
mseep_lodestar_mcp-0.1.4.dist-info/RECORD
