Metadata-Version: 2.4
Name: mseep-lodestar-mcp
Version: 0.1.4
Summary: Add your description here
Author-email: mseep <support@skydeck.ai>
Requires-Python: >=3.10
Requires-Dist: mcp[cli]>=1.2.1
Requires-Dist: pydantic>=2.10.6
